openGraphMatching/__init__.py
openGraphMatching/feature_preprocess.py
openGraphMatching/utils.py
openGraphMatching/matcher/BaseMatcher.py
openGraphMatching/matcher/CECIMatcher.py
openGraphMatching/matcher/GQLMatcher.py
openGraphMatching/matcher/NeuralMatcher.py
openGraphMatching/matcher/QuickSIMatcher.py
openGraphMatching/matcher/__init__.py
openGraphMatching/matcher/config.py
openGraphMatching/matcher/enumeraters.py
openGraphMatching/matcher/filters.py
openGraphMatching/matcher/models.py
openGraphMatching/matcher/orders.py
openGraphMatching-0.2.3.dist-info/LICENSE
openGraphMatching-0.2.3.dist-info/METADATA
openGraphMatching-0.2.3.dist-info/WHEEL
openGraphMatching-0.2.3.dist-info/top_level.txt
openGraphMatching-0.2.3.dist-info/RECORD
