Metadata-Version: 2.1
Name: openGraphMatching
Version: 0.2.3
Summary: A subgraph matching programming library.
Home-page: https://github.com/chang2000/openGraphMatching
Author: WANG Tianchang, LI Yuxiang
Author-email: tianchang.wang.00@gmail.com
License: UNKNOWN
Platform: UNKNOWN
Classifier: Programming Language :: Python :: 3
Classifier: License :: OSI Approved :: MIT License
Classifier: Operating System :: OS Independent
Requires-Python: >=3.6
